{
  "labResults": [
    {
      "id": "XRay",
      "name": "Chụp X Quang Tim, Phổi",
      "testResults": [
        {
          "result": "Bình thường",
          "detail": [
            {
              "name": "Phổi",
              "description": "Không có dấu hiệu viêm hoặc tổn thương.",
              "status": "Bình thường"
            },
            {
              "name": "Tim",
              "description": "Tim có kích thước bình thường.",
              "status": "Bình thường"
            }
          ],
          "notes": "Không phát hiện bất thường trên hình ảnh X-quang.",
          "images": ["https://example.com/xray1.jpg"]
        },
        {
          "result": "Bất thường nhẹ",
          "detail": [
            {
              "name": "Phổi",
              "description": "Có dấu hiệu tổn thương nhẹ ở phổi phải.",
              "status": "Bất thường"
            }
          ],
          "notes": "Cần kiểm tra thêm để xác định nguyên nhân.",
          "images": ["https://example.com/xray2.jpg"]
        },
        {
          "result": "Nghiêm trọng",
          "detail": [
            {
              "name": "Tim",
              "description": "Tim to bất thường, nghi ngờ suy tim.",
              "status": "Nghiêm trọng"
            }
          ],
          "notes": "Cần chuyển bệnh nhân đến bác sĩ chuyên khoa tim mạch.",
          "images": ["https://example.com/xray3.jpg"]
        }
      ]
    },
    {
      "id": "MRI",
      "name": "Chụp MRI",
      "testResults": [
        {
          "result": "Bình thường",
          "detail": [
            {
              "name": "Hình ảnh não",
              "description": "Không phát hiện tổn thương hoặc bất thường trong cấu trúc não.",
              "status": "Bình thường",
              "notes": "Kích thước não bình thường, không có dấu hiệu phù não.",
              "recommendations": "Không cần can thiệp, tiếp tục theo dõi sức khỏe định kỳ."
            },
            {
              "name": "Mạch máu não",
              "description": "Mạch máu thông suốt, không có dấu hiệu hẹp hoặc phình.",
              "status": "Bình thường",
              "notes": "Tuần hoàn máu trong não ổn định.",
              "recommendations": "Duy trì lối sống lành mạnh, tránh căng thẳng."
            }
          ],
          "notes": "Hình ảnh MRI không phát hiện bất kỳ bất thường nào.",
          "images": [
            "https://example.com/mri_normal1.jpg",
            "https://example.com/mri_normal2.jpg"
          ]
        },
        {
          "result": "Phát hiện bất thường",
          "detail": [
            {
              "name": "Hình ảnh não",
              "description": "Có vùng giảm tín hiệu ở thùy trán trái, kích thước 1.2cm x 1.0cm.",
              "status": "Bất thường",
              "notes": "Có khả năng là tổn thương dạng viêm hoặc u nhỏ.",
              "recommendations": "Khuyến cáo làm thêm xét nghiệm CT hoặc sinh thiết nếu cần thiết."
            },
            {
              "name": "Mạch máu não",
              "description": "Tắc nghẽn nhẹ ở động mạch cảnh phải (40%).",
              "status": "Bất thường",
              "notes": "Có dấu hiệu hẹp mạch, có nguy cơ nhồi máu não.",
              "recommendations": "Tham khảo bác sĩ tim mạch để điều trị."
            }
          ],
          "notes": "Cần theo dõi sát và điều trị kịp thời để tránh biến chứng.",
          "images": [
            "https://example.com/mri_abnormal1.jpg",
            "https://example.com/mri_abnormal2.jpg"
          ]
        },
        {
          "result": "Cảnh báo",
          "detail": [
            {
              "name": "Tủy sống",
              "description": "Phát hiện chèn ép tại vùng C4-C5 do thoái hóa đĩa đệm.",
              "status": "Nghiêm trọng",
              "notes": "Nguy cơ chèn ép dây thần kinh, gây đau nhức và giảm chức năng vận động.",
              "recommendations": "Cần can thiệp phẫu thuật hoặc vật lý trị liệu ngay lập tức."
            }
          ],
          "notes": "Bệnh nhân có triệu chứng nghiêm trọng, yêu cầu can thiệp khẩn cấp.",
          "images": ["https://example.com/mri_warning.jpg"]
        }
      ]
    },
    {
      "id": "BloodTest",
      "name": "Xét Nghiệm Máu",
      "testResults": [
        {
          "result": "Bình thường",
          "detail": [
            {
              "name": "Hemoglobin",
              "unit": "g/dL",
              "range": "12.0-16.0",
              "value": 14.5,
              "status": "Bình thường",
              "notes": "Mức hemoglobin trong giới hạn bình thường, đảm bảo đủ oxy trong máu.",
              "recommendations": "Duy trì chế độ ăn uống giàu chất sắt để ổn định chỉ số."
            },
            {
              "name": "WBC",
              "unit": "x10^9/L",
              "range": "4.0-11.0",
              "value": 6.8,
              "status": "Bình thường",
              "notes": "Không có dấu hiệu nhiễm trùng hoặc viêm nhiễm.",
              "recommendations": "Không cần can thiệp, tiếp tục theo dõi định kỳ."
            },
            {
              "name": "Glucose",
              "unit": "mmol/L",
              "range": "3.9-6.1",
              "value": 5.2,
              "status": "Bình thường",
              "notes": "Chỉ số đường huyết bình thường, không có dấu hiệu tiểu đường.",
              "recommendations": "Duy trì chế độ ăn uống lành mạnh, hạn chế đồ ngọt."
            }
          ],
          "notes": "Xét nghiệm máu không phát hiện bất thường.",
          "images": []
        },
        {
          "result": "Bất thường",
          "detail": [
            {
              "name": "Hemoglobin",
              "unit": "g/dL",
              "range": "12.0-16.0",
              "value": 10.8,
              "status": "Thiếu máu",
              "notes": "Chỉ số hemoglobin thấp, có dấu hiệu thiếu máu nhẹ.",
              "recommendations": "Khuyến cáo bổ sung sắt và kiểm tra nguyên nhân thiếu máu."
            },
            {
              "name": "WBC",
              "unit": "x10^9/L",
              "range": "4.0-11.0",
              "value": 12.5,
              "status": "Tăng cao",
              "notes": "Chỉ số bạch cầu tăng cao, có khả năng nhiễm trùng.",
              "recommendations": "Kiểm tra thêm để xác định nguồn gốc nhiễm trùng."
            }
          ],
          "notes": "Phát hiện bất thường nhẹ, cần kiểm tra và điều trị kịp thời.",
          "images": []
        },
        {
          "result": "Cảnh báo",
          "detail": [
            {
              "name": "Tiểu cầu",
              "unit": "x10^9/L",
              "range": "150-450",
              "value": 48,
              "status": "Nguy cơ xuất huyết",
              "notes": "Số lượng tiểu cầu rất thấp, có nguy cơ xuất huyết tự nhiên.",
              "recommendations": "Cần nhập viện và truyền tiểu cầu khẩn cấp."
            }
          ],
          "notes": "Tình trạng nghiêm trọng, yêu cầu xử lý ngay.",
          "images": []
        }
      ]
    }
  ]
}
